fc_smy_bigdata.py
fc_smy-1.0.dist-info/METADATA
fc_smy-1.0.dist-info/WHEEL
fc_smy-1.0.dist-info/top_level.txt
fc_smy-1.0.dist-info/RECORD
