Metadata-Version: 2.1
Name: fc-smy
Version: 1.0
Summary: 计算机3班
Home-page: UNKNOWN
Author: 计算机3班
Author-email: fc@bigdata.com
License: UNKNOWN
Platform: UNKNOWN
